dec_ansi_parser/__init__.py
dec_ansi_parser/formatter.py
dec_ansi_parser/parser.py
dec_ansi_parser/script_reader.py
dec_ansi_parser-0.2.0.dist-info/LICENSE
dec_ansi_parser-0.2.0.dist-info/METADATA
dec_ansi_parser-0.2.0.dist-info/WHEEL
dec_ansi_parser-0.2.0.dist-info/entry_points.txt
dec_ansi_parser-0.2.0.dist-info/RECORD
