Metadata-Version: 2.1
Name: dec-ansi-parser
Version: 0.2.0
Summary: Terminal control sequence parser
License: BSD 3-Clause
Author: yut23
Requires-Python: >=3.8,<4.0
Classifier: License :: Other/Proprietary License
Classifier: Programming Language :: Python :: 3
Classifier: Programming Language :: Python :: 3.8
Classifier: Programming Language :: Python :: 3.9
Classifier: Programming Language :: Python :: 3.10
Classifier: Programming Language :: Python :: 3.11
